LICENSE
MANIFEST.in
README.md
setup.py
magicblue/__init__.py
magicblue/magicbluelib.py
magicblue/magicblueshell.py
magicblue.egg-info/PKG-INFO
magicblue.egg-info/SOURCES.txt
magicblue.egg-info/dependency_links.txt
magicblue.egg-info/entry_points.txt
magicblue.egg-info/requires.txt
magicblue.egg-info/top_level.txt