Metadata-Version: 1.1
Name: magicblue
Version: 0.6.0
Summary: Unofficial Python API to control Magic Blue bulbs over Bluetooth
Home-page: https://github.com/Betree/pyMagicBlue
Author: Benjamin Piouffle
Author-email: benjamin.piouffle@gmail.com
License: MIT
Keywords: bluetooth,bulb,magic,blue,ble,iot
Platform: UNKNOWN
Classifier: Development Status :: 4 - Beta
Classifier: Programming Language :: Python :: 3 :: Only
Classifier: License :: OSI Approved :: MIT License
Classifier: Natural Language :: English
